rust_pypi_example.cp36-win32.pyd
rust_pypi_example/__init__.py
rust_pypi_example/cli.py
rust_pypi_example/rust_pypi_example.py
rust_pypi_example/rust/Cargo.toml
rust_pypi_example/rust/src/lib.rs
rust_pypi_example/rust/src/rust_pypi_example.h
rust_pypi_example/rust/target/release/rust_pypi_example.dll
rust_pypi_example/rust/target/release/deps/rust_pypi_example.dll
rust_pypi_example/rust/target/release/deps/rust_pypi_example.dll.lib
rust_pypi_example-0.8.7.dist-info/DESCRIPTION.rst
rust_pypi_example-0.8.7.dist-info/METADATA
rust_pypi_example-0.8.7.dist-info/RECORD
rust_pypi_example-0.8.7.dist-info/WHEEL
rust_pypi_example-0.8.7.dist-info/entry_points.txt
rust_pypi_example-0.8.7.dist-info/metadata.json
rust_pypi_example-0.8.7.dist-info/top_level.txt
