Metadata-Version: 2.0
Name: rust-pypi-example
Version: 0.8.7
Summary: Python Boilerplate contains all the boilerplate you need to create a Python wheel with Rust.
Home-page: https://github.com/mckaymatt/rust_pypi_example
Author: Matt McKay
Author-email: mckaymatt@gmail.com
License: Apache Software License 2.0
Keywords: rust_pypi_example
Platform: UNKNOWN
Classifier: Development Status :: 2 - Pre-Alpha
Classifier: Intended Audience :: Developers
Classifier: License :: OSI Approved :: Apache Software License
Classifier: Natural Language :: English
Classifier: Programming Language :: Python :: 2
Classifier: Programming Language :: Python :: 2.6
Classifier: Programming Language :: Python :: 2.7
Classifier: Programming Language :: Python :: 3
Classifier: Programming Language :: Python :: 3.3
Classifier: Programming Language :: Python :: 3.4
Classifier: Programming Language :: Python :: 3.5
Requires-Dist: Click (>=6.0)
Requires-Dist: cffi (>=1.0.0)
